pyomnidata/GetOMNI.py
pyomnidata/GetSolarFlux.py
pyomnidata/Globals.py
pyomnidata/PlotOMNI.py
pyomnidata/ReadOMNI.py
pyomnidata/UpdateLocalData.py
pyomnidata/UpdateSolarFlux.py
pyomnidata/_CompareUpdates.py
pyomnidata/_ConvertFTPFile.py
pyomnidata/_ConvertSolarFlux.py
pyomnidata/_DTPlotLabel.py
pyomnidata/_DeleteFTPFile.py
pyomnidata/_DownloadF107.py
pyomnidata/_DownloadFTPFile.py
pyomnidata/_DownloadFTPIndex.py
pyomnidata/_ParseFTP.py
pyomnidata/_ReadDataIndex.py
pyomnidata/_ReadSolarFlux.py
pyomnidata/_UpdateDataIndex.py
pyomnidata/__init__.py
pyomnidata-1.0.2.dist-info/licenses/LICENSE
pyomnidata-1.0.2.dist-info/METADATA
pyomnidata-1.0.2.dist-info/WHEEL
pyomnidata-1.0.2.dist-info/top_level.txt
pyomnidata-1.0.2.dist-info/RECORD
