Metadata-Version: 2.4
Name: pyomnidata
Version: 1.0.2
Summary: Python tool for downloading, converting and reading OMNI solar wind data.
Home-page: https://github.com/mattkjames7/pyomnidata
Author: Matthew Knight James
Author-email: mattkjames7@gmail.com
Classifier: Programming Language :: Python :: 3
Classifier: License :: OSI Approved :: MIT License
Classifier: Operating System :: POSIX
License-File: LICENSE
Requires-Dist: numpy
Requires-Dist: matplotlib
Requires-Dist: RecarrayTools
Requires-Dist: PyFileIO
Requires-Dist: DateTimeTools>=1.0.1
Requires-Dist: requests
Dynamic: author
Dynamic: author-email
Dynamic: classifier
Dynamic: description
Dynamic: description-content-type
Dynamic: home-page
Dynamic: license-file
Dynamic: requires-dist
Dynamic: summary
